celery_sqlalchemy/__init__.py
celery_sqlalchemy/celery.py
celery_sqlalchemy/errors.py
celery_sqlalchemy/json/__init__.py
celery_sqlalchemy/json/postgresql.py
celery_sqlalchemy/json/sqlalchemy.py
celery_sqlalchemy/model/__init__.py
celery_sqlalchemy/model/postgresql_1_4.py
celery_sqlalchemy/model/postgresql_2_0.py
celery_sqlalchemy/model/sqlalchemy_1_4.py
celery_sqlalchemy/model/sqlalchemy_2_0.py
celery_sqlalchemy/py.typed
celery_sqlalchemy/schema.py
celery_sqlalchemy/types.py
celery_sqlalchemy-0.1.6.dist-info/LICENSE
celery_sqlalchemy-0.1.6.dist-info/METADATA
celery_sqlalchemy-0.1.6.dist-info/WHEEL
celery_sqlalchemy-0.1.6.dist-info/RECORD
