Metadata-Version: 2.1
Name: celery-sqlalchemy
Version: 0.1.6
Summary: SQLAlchemy model serialization for celery.
Home-page: https://github.com/seankerr/py-celery-sqlalchemy
License: BSD-3-Clause
Keywords: celery,sqlalchemy,serialization
Author: Sean Kerr
Author-email: sean@code-box.org
Requires-Python: >=3.9,<4.0
Classifier: License :: OSI Approved :: BSD License
Classifier: Programming Language :: Python :: 3
Classifier: Programming Language :: Python :: 3.9
Classifier: Programming Language :: Python :: 3.10
Classifier: Programming Language :: Python :: 3.11
Requires-Dist: orjson (>3.9.3)
Requires-Dist: sqlalchemy (>1.3)
Project-URL: Repository, https://github.com/seankerr/py-celery-sqlalchemy
